transcend/__init__.py
transcend/__main__.py
transcend/cli.py
transcend/exceptions.py
transcend/faststart.py
transcend/ffmpeg.py
transcend/output.py
transcend/probe.py
transcend/codec/__init__.py
transcend/codec/_codec.py
transcend/codec/audio/__init__.py
transcend/codec/audio/aac.py
transcend/codec/audio/flac.py
transcend/codec/audio/mp3.py
transcend/codec/audio/opus.py
transcend/codec/audio/vorbis.py
transcend/codec/subtitle/__init__.py
transcend/codec/subtitle/sami.py
transcend/codec/subtitle/srt.py
transcend/codec/subtitle/ssa.py
transcend/codec/subtitle/webvtt.py
transcend/codec/video/__init__.py
transcend/codec/video/h264.py
transcend/codec/video/h265.py
transcend/codec/video/theora.py
transcend/codec/video/vpx.py
transcend/coding/__init__.py
transcend/coding/cli.py
transcend/coding/exceptions.py
transcend/coding/faststart.py
transcend/coding/ffmpeg.py
transcend/coding/output.py
transcend/coding/probe.py
transcend/ext/__init__.py
transcend/format/__init__.py
transcend/format/_container.py
transcend/format/aac.py
transcend/format/aiff.py
transcend/format/asf.py
transcend/format/chromaprint.py
transcend/format/gif.py
transcend/format/hashing.py
transcend/format/image2.py
transcend/format/matroska.py
transcend/format/mp3.py
transcend/format/mp4.py
transcend/format/mpegts.py
transcend/format/null.py
transcend/format/nut.py
transcend/format/ogg.py
transcend/format/streaming/__init__.py
transcend/format/streaming/dash.py
transcend/format/streaming/hls.py
transcend/format/streaming/segment.py
transcend/format/streaming/smooth.py
transcend/format/streaming/webm.py
transcend/preset/__init__.py
transcend/preset/thumbs.py
transcend/preset/audio/__init__.py
transcend/preset/audio/aac.py
transcend/preset/audio/flac.py
transcend/preset/audio/mp3.py
transcend/preset/audio/opus.py
transcend/preset/audio/vorbis.py
transcend/preset/subtitle/__init__.py
transcend/preset/subtitle/sami.py
transcend/preset/subtitle/srt.py
transcend/preset/subtitle/ssa.py
transcend_py-0.1.13.dist-info/LICENSE
transcend_py-0.1.13.dist-info/METADATA
transcend_py-0.1.13.dist-info/WHEEL
transcend_py-0.1.13.dist-info/top_level.txt
transcend_py-0.1.13.dist-info/RECORD
