Metadata-Version: 2.1
Name: transcend-py
Version: 0.1.13
Summary: High performance video and audio transcoding for aliens.
Home-page: https://github.com/jaredlunde/transcend
Author: Jared Lunde
Author-email: jared.lunde@gmail.com
License: MIT
Platform: UNKNOWN
Requires-Dist: boto3
Requires-Dist: humanfriendly
Requires-Dist: psutil
Requires-Dist: vital-tools
Requires-Dist: awstools-py
